pyfortune.py
setup.py
PyFortune.egg-info/PKG-INFO
PyFortune.egg-info/SOURCES.txt
PyFortune.egg-info/dependency_links.txt
PyFortune.egg-info/entry_points.txt
PyFortune.egg-info/top_level.txt
pyfortune/CompiledFortuneFile.py
pyfortune/FortuneFile.py
pyfortune/__init__.py
pyfortune/__main__.py
pyfortune/compile.py
pyfortune/entry.py
pyfortune/loader.py
pyfortune/path.py
pyfortune/data/art
pyfortune/data/ascii-art
pyfortune/data/computers
pyfortune/data/cookie
pyfortune/data/debian
pyfortune/data/definitions
pyfortune/data/disclaimer
pyfortune/data/drugs
pyfortune/data/education
pyfortune/data/ethnic
pyfortune/data/food
pyfortune/data/fortunes
pyfortune/data/goedel
pyfortune/data/humorists
pyfortune/data/kids
pyfortune/data/knghtbrd
pyfortune/data/law
pyfortune/data/linux
pyfortune/data/linuxcookie
pyfortune/data/literature
pyfortune/data/love
pyfortune/data/magic
pyfortune/data/medicine
pyfortune/data/men-women
pyfortune/data/miscellaneous
pyfortune/data/news
pyfortune/data/paradoxum
pyfortune/data/people
pyfortune/data/perl
pyfortune/data/pets
pyfortune/data/platitudes
pyfortune/data/politics
pyfortune/data/pratchett
pyfortune/data/riddles
pyfortune/data/science
pyfortune/data/songs-poems
pyfortune/data/sports
pyfortune/data/startrek
pyfortune/data/tao
pyfortune/data/translate-me
pyfortune/data/wisdom
pyfortune/data/work
pyfortune/data/zippy
pyfortune/data/off/art
pyfortune/data/off/astrology
pyfortune/data/off/atheism
pyfortune/data/off/black-humor
pyfortune/data/off/cookie
pyfortune/data/off/debian
pyfortune/data/off/definitions
pyfortune/data/off/drugs
pyfortune/data/off/ethnic
pyfortune/data/off/fortunes
pyfortune/data/off/hphobia
pyfortune/data/off/limerick
pyfortune/data/off/linux
pyfortune/data/off/misandry
pyfortune/data/off/miscellaneous
pyfortune/data/off/misogyny
pyfortune/data/off/politics
pyfortune/data/off/privates
pyfortune/data/off/racism
pyfortune/data/off/religion
pyfortune/data/off/riddles
pyfortune/data/off/sex
pyfortune/data/off/songs-poems
pyfortune/data/off/vulgarity
pyfortune/data/off/zippy