Metadata-Version: 1.1
Name: PyFortune
Version: 0.1
Summary: Port of the classic fortune program to python
Home-page: https://github.com/xiaomao5/pyfortune
Author: xiaomao
Author-email: xiaomao5@live.com
License: UNKNOWN
Keywords: fortune port unix game
Platform: UNKNOWN
Classifier: Development Status :: 3 - Alpha
Classifier: Environment :: Console
Classifier: Intended Audience :: End Users/Desktop
Classifier: Intended Audience :: Developers
Classifier: Intended Audience :: System Administrators
Classifier: License :: OSI Approved :: GNU General Public License v3 or later (GPLv3+)
Classifier: Natural Language :: English
Classifier: Operating System :: MacOS :: MacOS X
Classifier: Operating System :: Microsoft :: Windows
Classifier: Operating System :: POSIX
Classifier: Programming Language :: Python
Classifier: Topic :: Games/Entertainment
Classifier: Topic :: Utilities
